AUTHORS
ChangeLog
MANIFEST.in
README.rst
requirements.txt
setup.cfg
setup.py
leonardo_cookie_law/__init__.py
leonardo_cookie_law.egg-info/PKG-INFO
leonardo_cookie_law.egg-info/SOURCES.txt
leonardo_cookie_law.egg-info/dependency_links.txt
leonardo_cookie_law.egg-info/not-zip-safe
leonardo_cookie_law.egg-info/pbr.json
leonardo_cookie_law.egg-info/requires.txt
leonardo_cookie_law.egg-info/top_level.txt
leonardo_cookie_law/locale/cs/LC_MESSAGES/django.mo
leonardo_cookie_law/locale/cs/LC_MESSAGES/django.po
leonardo_cookie_law/locale/en/LC_MESSAGES/django.mo
leonardo_cookie_law/locale/en/LC_MESSAGES/django.po
leonardo_cookie_law/templates/cookielaw/banner.html
leonardo_cookie_law/templates/widget/cookielaw/default.html
leonardo_cookie_law/widget/__init__.py
leonardo_cookie_law/widget/cookielaw/__init__.py
leonardo_cookie_law/widget/cookielaw/models.py